[
    {
        "spam": "0",
        "advertisement": "0",
        "irrelevant_content": "0",
        "non_visitor_rant": "0",
        "toxicity": "0",
        "job_id": 22992
    },
    {
        "spam": "0",
        "advertisement": "0",
        "irrelevant_content": "0",
        "non_visitor_rant": "0",
        "toxicity": "1",
        "job_id": 47640
    },
    {
        "spam": "0",
        "advertisement": "0",
        "irrelevant_content": "0",
        "non_visitor_rant": "0",
        "toxicity": "0",
        "job_id": 50796
    },
    {
        "spam": "0",
        "advertisement": "0",
        "irrelevant_content": "0",
        "non_visitor_rant": "0",
        "toxicity": "0",
        "job_id": 4407
    },
    {
        "spam": "0",
        "advertisement": "0",
        "irrelevant_content": "0",
        "non_visitor_rant": "0",
        "toxicity": "0",
        "job_id": 47878
    },
    {
        "spam": "0",
        "advertisement": "0",
        "irrelevant_content": "0",
        "non_visitor_rant": "0",
        "toxicity": "0",
        "job_id": 36458
    },
    {
        "spam": "0",
        "advertisement": "0",
        "irrelevant_content": "0",
        "non_visitor_rant": "0",
        "toxicity": "0",
        "job_id": 27334
    },
    {
        "spam": "0",
        "advertisement": "0",
        "irrelevant_content": "0",
        "non_visitor_rant": "0",
        "toxicity": "0",
        "job_id": 20973
    },
    {
        "spam": "0",
        "advertisement": "0",
        "irrelevant_content": "0",
        "non_visitor_rant": "0",
        "toxicity": "0",
        "job_id": 5395
    },
    {
        "spam": "0",
        "advertisement": "0",
        "irrelevant_content": "0",
        "non_visitor_rant": "0",
        "toxicity": "0",
        "job_id": 37475
    },
    {
        "spam": "0",
        "advertisement": "0",
        "irrelevant_content": "0",
        "non_visitor_rant": "0",
        "toxicity": "0",
        "job_id": 19496
    },
    {
        "spam": "0",
        "advertisement": "0",
        "irrelevant_content": "0",
        "non_visitor_rant": "0",
        "toxicity": "0",
        "job_id": 31916
    },
    {
        "spam": "0",
        "advertisement": "0",
        "irrelevant_content": "0",
        "non_visitor_rant": "0",
        "toxicity": "0",
        "job_id": 44227
    },
    {
        "spam": "0",
        "advertisement": "0",
        "irrelevant_content": "0",
        "non_visitor_rant": "0",
        "toxicity": "0",
        "job_id": 12957
    },
    {
        "spam": "0",
        "advertisement": "0",
        "irrelevant_content": "0",
        "non_visitor_rant": "0",
        "toxicity": "0",
        "job_id": 1954
    },
    {
        "spam": "0",
        "advertisement": "0",
        "irrelevant_content": "0",
        "non_visitor_rant": "0",
        "toxicity": "0",
        "job_id": 43317
    },
    {
        "spam": "0",
        "advertisement": "0",
        "irrelevant_content": "0",
        "non_visitor_rant": "0",
        "toxicity": "0",
        "job_id": 20912
    },
    {
        "spam": "0",
        "advertisement": "0",
        "irrelevant_content": "0",
        "non_visitor_rant": "0",
        "toxicity": "0",
        "job_id": 19682
    },
    {
        "spam": "0",
        "advertisement": "0",
        "irrelevant_content": "0",
        "non_visitor_rant": "0",
        "toxicity": "1",
        "job_id": 37622
    },
    {
        "spam": "0",
        "advertisement": "0",
        "irrelevant_content": "0",
        "non_visitor_rant": "0",
        "toxicity": "0",
        "job_id": 34126
    }
]