[
    {
        "spam": "0",
        "advertisement": "0",
        "irrelevant_content": "0",
        "non_visitor_rant": "0",
        "toxicity": "0",
        "job_id": 28135
    },
    {
        "spam": "0",
        "advertisement": "0",
        "irrelevant_content": "0",
        "non_visitor_rant": "0",
        "toxicity": "0",
        "job_id": 53019
    },
    {
        "spam": "0",
        "advertisement": "0",
        "irrelevant_content": "0",
        "non_visitor_rant": "0",
        "toxicity": "0",
        "job_id": 8551
    },
    {
        "spam": "0",
        "advertisement": "0",
        "irrelevant_content": "0",
        "non_visitor_rant": "0",
        "toxicity": "0",
        "job_id": 37301
    },
    {
        "spam": "0",
        "advertisement": "0",
        "irrelevant_content": "0",
        "non_visitor_rant": "0",
        "toxicity": "0",
        "job_id": 52223
    },
    {
        "spam": "0",
        "advertisement": "0",
        "irrelevant_content": "0",
        "non_visitor_rant": "0",
        "toxicity": "0",
        "job_id": 5234
    },
    {
        "spam": "0",
        "advertisement": "0",
        "irrelevant_content": "0",
        "non_visitor_rant": "0",
        "toxicity": "0",
        "job_id": 29110
    },
    {
        "spam": "0",
        "advertisement": "0",
        "irrelevant_content": "0",
        "non_visitor_rant": "0",
        "toxicity": "0",
        "job_id": 19012
    },
    {
        "spam": "0",
        "advertisement": "0",
        "irrelevant_content": "0",
        "non_visitor_rant": "0",
        "toxicity": "0",
        "job_id": 41953
    },
    {
        "spam": "0",
        "advertisement": "0",
        "irrelevant_content": "0",
        "non_visitor_rant": "0",
        "toxicity": "0",
        "job_id": 12551
    },
    {
        "spam": "0",
        "advertisement": "0",
        "irrelevant_content": "0",
        "non_visitor_rant": "0",
        "toxicity": "0",
        "job_id": 36003
    },
    {
        "spam": "0",
        "advertisement": "0",
        "irrelevant_content": "0",
        "non_visitor_rant": "0",
        "toxicity": "0",
        "job_id": 42950
    },
    {
        "spam": "0",
        "advertisement": "0",
        "irrelevant_content": "0",
        "non_visitor_rant": "0",
        "toxicity": "0",
        "job_id": 52682
    },
    {
        "spam": "0",
        "advertisement": "0",
        "irrelevant_content": "0",
        "non_visitor_rant": "0",
        "toxicity": "0",
        "job_id": 49340
    },
    {
        "spam": "0",
        "advertisement": "0",
        "irrelevant_content": "0",
        "non_visitor_rant": "0",
        "toxicity": "0",
        "job_id": 1709
    },
    {
        "spam": "0",
        "advertisement": "0",
        "irrelevant_content": "0",
        "non_visitor_rant": "0",
        "toxicity": "0",
        "job_id": 45856
    },
    {
        "spam": "0",
        "advertisement": "0",
        "irrelevant_content": "0",
        "non_visitor_rant": "0",
        "toxicity": "0",
        "job_id": 51719
    },
    {
        "spam": "0",
        "advertisement": "0",
        "irrelevant_content": "0",
        "non_visitor_rant": "0",
        "toxicity": "0",
        "job_id": 48557
    },
    {
        "spam": "0",
        "advertisement": "0",
        "irrelevant_content": "0",
        "non_visitor_rant": "1",
        "toxicity": "0",
        "job_id": 5647
    },
    {
        "spam": "0",
        "advertisement": "0",
        "irrelevant_content": "0",
        "non_visitor_rant": "0",
        "toxicity": "0",
        "job_id": 21072
    }
]