[
    {
        "spam": "0",
        "advertisement": "0",
        "irrelevant_content": "0",
        "non_visitor_rant": "0",
        "toxicity": "0",
        "job_id": 3723
    },
    {
        "spam": "0",
        "advertisement": "0",
        "irrelevant_content": "0",
        "non_visitor_rant": "0",
        "toxicity": "0",
        "job_id": 30422
    },
    {
        "spam": "0",
        "advertisement": "0",
        "irrelevant_content": "0",
        "non_visitor_rant": "0",
        "toxicity": "0",
        "job_id": 20822
    },
    {
        "spam": "0",
        "advertisement": "0",
        "irrelevant_content": "0",
        "non_visitor_rant": "0",
        "toxicity": "0",
        "job_id": 8810
    },
    {
        "spam": "0",
        "advertisement": "0",
        "irrelevant_content": "0",
        "non_visitor_rant": "0",
        "toxicity": "0",
        "job_id": 3281
    },
    {
        "spam": "0",
        "advertisement": "0",
        "irrelevant_content": "0",
        "non_visitor_rant": "0",
        "toxicity": "0",
        "job_id": 22637
    },
    {
        "spam": "0",
        "advertisement": "0",
        "irrelevant_content": "0",
        "non_visitor_rant": "0",
        "toxicity": "0",
        "job_id": 13700
    },
    {
        "spam": "0",
        "advertisement": "0",
        "irrelevant_content": "0",
        "non_visitor_rant": "0",
        "toxicity": "0",
        "job_id": 39615
    },
    {
        "spam": "0",
        "advertisement": "0",
        "irrelevant_content": "0",
        "non_visitor_rant": "0",
        "toxicity": "0",
        "job_id": 47197
    },
    {
        "spam": "0",
        "advertisement": "0",
        "irrelevant_content": "0",
        "non_visitor_rant": "0",
        "toxicity": "0",
        "job_id": 50660
    },
    {
        "spam": "0",
        "advertisement": "0",
        "irrelevant_content": "0",
        "non_visitor_rant": "0",
        "toxicity": "0",
        "job_id": 7732
    },
    {
        "spam": "0",
        "advertisement": "0",
        "irrelevant_content": "0",
        "non_visitor_rant": "0",
        "toxicity": "0",
        "job_id": 43071
    },
    {
        "spam": "0",
        "advertisement": "0",
        "irrelevant_content": "1",
        "non_visitor_rant": "0",
        "toxicity": "0",
        "job_id": 17503
    },
    {
        "spam": "0",
        "advertisement": "0",
        "irrelevant_content": "0",
        "non_visitor_rant": "0",
        "toxicity": "0",
        "job_id": 46306
    },
    {
        "spam": "0",
        "advertisement": "0",
        "irrelevant_content": "0",
        "non_visitor_rant": "0",
        "toxicity": "0",
        "job_id": 9701
    },
    {
        "spam": "0",
        "advertisement": "0",
        "irrelevant_content": "0",
        "non_visitor_rant": "0",
        "toxicity": "0",
        "job_id": 34378
    },
    {
        "spam": "0",
        "advertisement": "0",
        "irrelevant_content": "0",
        "non_visitor_rant": "0",
        "toxicity": "0",
        "job_id": 52984
    },
    {
        "spam": "0",
        "advertisement": "0",
        "irrelevant_content": "0",
        "non_visitor_rant": "0",
        "toxicity": "0",
        "job_id": 6319
    },
    {
        "spam": "0",
        "advertisement": "0",
        "irrelevant_content": "0",
        "non_visitor_rant": "0",
        "toxicity": "0",
        "job_id": 10118
    },
    {
        "spam": "0",
        "advertisement": "0",
        "irrelevant_content": "0",
        "non_visitor_rant": "0",
        "toxicity": "0",
        "job_id": 20367
    }
]