[
    {
        "spam": "0",
        "advertisement": "0",
        "irrelevant_content": "0",
        "non_visitor_rant": "0",
        "toxicity": "0",
        "job_id": 33249
    },
    {
        "spam": "0",
        "advertisement": "0",
        "irrelevant_content": "0",
        "non_visitor_rant": "0",
        "toxicity": "0",
        "job_id": 45489
    },
    {
        "spam": "0",
        "advertisement": "0",
        "irrelevant_content": "0",
        "non_visitor_rant": "0",
        "toxicity": "0",
        "job_id": 15681
    },
    {
        "spam": "0",
        "advertisement": "0",
        "irrelevant_content": "0",
        "non_visitor_rant": "0",
        "toxicity": "0",
        "job_id": 8443
    },
    {
        "spam": "0",
        "advertisement": "0",
        "irrelevant_content": "0",
        "non_visitor_rant": "0",
        "toxicity": "0",
        "job_id": 13791
    },
    {
        "spam": "0",
        "advertisement": "0",
        "irrelevant_content": "0",
        "non_visitor_rant": "0",
        "toxicity": "0",
        "job_id": 49419
    },
    {
        "spam": "0",
        "advertisement": "0",
        "irrelevant_content": "0",
        "non_visitor_rant": "0",
        "toxicity": "1",
        "job_id": 43220
    },
    {
        "spam": "0",
        "advertisement": "0",
        "irrelevant_content": "0",
        "non_visitor_rant": "0",
        "toxicity": "0",
        "job_id": 37319
    },
    {
        "spam": "0",
        "advertisement": "0",
        "irrelevant_content": "0",
        "non_visitor_rant": "0",
        "toxicity": "0",
        "job_id": 30069
    },
    {
        "spam": "0",
        "advertisement": "0",
        "irrelevant_content": "0",
        "non_visitor_rant": "0",
        "toxicity": "0",
        "job_id": 14076
    },
    {
        "spam": "0",
        "advertisement": "0",
        "irrelevant_content": "0",
        "non_visitor_rant": "0",
        "toxicity": "0",
        "job_id": 15806
    },
    {
        "spam": "0",
        "advertisement": "0",
        "irrelevant_content": "0",
        "non_visitor_rant": "0",
        "toxicity": "0",
        "job_id": 45791
    },
    {
        "spam": "0",
        "advertisement": "0",
        "irrelevant_content": "0",
        "non_visitor_rant": "0",
        "toxicity": "0",
        "job_id": 50994
    },
    {
        "spam": "0",
        "advertisement": "0",
        "irrelevant_content": "0",
        "non_visitor_rant": "0",
        "toxicity": "0",
        "job_id": 12169
    },
    {
        "spam": "0",
        "advertisement": "0",
        "irrelevant_content": "0",
        "non_visitor_rant": "0",
        "toxicity": "0",
        "job_id": 3955
    },
    {
        "spam": "0",
        "advertisement": "0",
        "irrelevant_content": "0",
        "non_visitor_rant": "0",
        "toxicity": "0",
        "job_id": 24823
    },
    {
        "spam": "0",
        "advertisement": "0",
        "irrelevant_content": "0",
        "non_visitor_rant": "0",
        "toxicity": "0",
        "job_id": 24339
    },
    {
        "spam": "0",
        "advertisement": "0",
        "irrelevant_content": "0",
        "non_visitor_rant": "0",
        "toxicity": "0",
        "job_id": 35756
    },
    {
        "spam": "0",
        "advertisement": "0",
        "irrelevant_content": "0",
        "non_visitor_rant": "0",
        "toxicity": "0",
        "job_id": 45737
    },
    {
        "spam": "0",
        "advertisement": "0",
        "irrelevant_content": "0",
        "non_visitor_rant": "0",
        "toxicity": "0",
        "job_id": 21967
    }
]