[
    {
        "spam": "0",
        "advertisement": "0",
        "irrelevant_content": "0",
        "non_visitor_rant": "0",
        "toxicity": "0",
        "job_id": 45050
    },
    {
        "spam": "0",
        "advertisement": "0",
        "irrelevant_content": "0",
        "non_visitor_rant": "0",
        "toxicity": "0",
        "job_id": 43443
    },
    {
        "spam": "0",
        "advertisement": "0",
        "irrelevant_content": "0",
        "non_visitor_rant": "0",
        "toxicity": "0",
        "job_id": 47956
    },
    {
        "spam": "0",
        "advertisement": "0",
        "irrelevant_content": "0",
        "non_visitor_rant": "0",
        "toxicity": "0",
        "job_id": 9988
    },
    {
        "spam": "0",
        "advertisement": "0",
        "irrelevant_content": "0",
        "non_visitor_rant": "0",
        "toxicity": "0",
        "job_id": 22157
    },
    {
        "spam": "0",
        "advertisement": "0",
        "irrelevant_content": "0",
        "non_visitor_rant": "0",
        "toxicity": "0",
        "job_id": 40178
    },
    {
        "spam": "0",
        "advertisement": "0",
        "irrelevant_content": "0",
        "non_visitor_rant": "0",
        "toxicity": "0",
        "job_id": 43308
    },
    {
        "spam": "0",
        "advertisement": "0",
        "irrelevant_content": "0",
        "non_visitor_rant": "0",
        "toxicity": "0",
        "job_id": 47576
    },
    {
        "spam": "0",
        "advertisement": "0",
        "irrelevant_content": "0",
        "non_visitor_rant": "0",
        "toxicity": "0",
        "job_id": 29214
    },
    {
        "spam": "0",
        "advertisement": "0",
        "irrelevant_content": "0",
        "non_visitor_rant": "0",
        "toxicity": "0",
        "job_id": 18035
    },
    {
        "spam": "0",
        "advertisement": "0",
        "irrelevant_content": "0",
        "non_visitor_rant": "0",
        "toxicity": "0",
        "job_id": 5228
    },
    {
        "spam": "0",
        "advertisement": "0",
        "irrelevant_content": "0",
        "non_visitor_rant": "0",
        "toxicity": "1",
        "job_id": 20029
    },
    {
        "spam": "0",
        "advertisement": "0",
        "irrelevant_content": "0",
        "non_visitor_rant": "0",
        "toxicity": "0",
        "job_id": 10406
    },
    {
        "spam": "0",
        "advertisement": "0",
        "irrelevant_content": "0",
        "non_visitor_rant": "0",
        "toxicity": "0",
        "job_id": 114
    },
    {
        "spam": "0",
        "advertisement": "0",
        "irrelevant_content": "0",
        "non_visitor_rant": "0",
        "toxicity": "0",
        "job_id": 4119
    },
    {
        "spam": "0",
        "advertisement": "0",
        "irrelevant_content": "0",
        "non_visitor_rant": "0",
        "toxicity": "0",
        "job_id": 12946
    },
    {
        "spam": "0",
        "advertisement": "0",
        "irrelevant_content": "0",
        "non_visitor_rant": "0",
        "toxicity": "0",
        "job_id": 51718
    },
    {
        "spam": "0",
        "advertisement": "0",
        "irrelevant_content": "0",
        "non_visitor_rant": "0",
        "toxicity": "0",
        "job_id": 32520
    },
    {
        "spam": "0",
        "advertisement": "0",
        "irrelevant_content": "0",
        "non_visitor_rant": "0",
        "toxicity": "0",
        "job_id": 44081
    },
    {
        "spam": "0",
        "advertisement": "0",
        "irrelevant_content": "0",
        "non_visitor_rant": "0",
        "toxicity": "0",
        "job_id": 37031
    }
]